moedas/__init__.py
moedas/asd.py
moedas/coin.py
PACOTES_DE_ACOES-0.0.1.dist-info/LICENCE
PACOTES_DE_ACOES-0.0.1.dist-info/METADATA
PACOTES_DE_ACOES-0.0.1.dist-info/WHEEL
PACOTES_DE_ACOES-0.0.1.dist-info/top_level.txt
PACOTES_DE_ACOES-0.0.1.dist-info/RECORD
