Metadata-Version: 2.1
Name: PACOTES-DE-ACOES
Version: 0.0.1
Summary: biblioteca com dados basicos sobre cotaçẽs de moedas e ações
Home-page: UNKNOWN
Author: Clístenes Rodger e Marcos Eduardo
Author-email: clistenes090@hotmail.com
License: MIT License
Keywords: moedas_acoes_2023
Platform: UNKNOWN
License-File: LICENCE
Requires-Dist: matplotlib
Requires-Dist: pandas
Requires-Dist: pandas-datareader
Requires-Dist: requests
Requires-Dist: yfinance
